{
  "archive": {
    "service": "DocumentService",
    "method": "CreateDocument",
    "parameter": {
      "AccessCode": "<<<accessCode>>>",
      "AccessGroup": "<<<accessGroup>>>",
      "Archive": "Saksdokument",
      "CaseNumber": "<<<caseNumber>>>",
      "Category": "Dokument ut",
      "DocumentDate": "<<<date>>>",
      "Paragraph": "<<<paragraph>>>",
      "ResponsiblePersonEmail": "<<<responsiblePersonEmail>>>",
      "Status": "R",
      "Title": "<<<title>>>",
      "UnofficialTitle": "<<<title>>>"
    }
  },
  "data": {
    "accessGroup": "Elev vgs",
    "accessCode": "U",
    "caseNumber": "30/00000",
    "date": "2021-09-27",
    "title": "Saken om kjeks",
    "responsiblePersonEmail": "kjell.t.ring@vtfk.no",
    "paragraph": "Ingen paragraf gitt"
  }
}
